naga_gwas_rest-0.7.1.data/scripts/naga_taskrunner.py
nbgwas_rest/__init__.py
nbgwas_rest/naga_taskrunner.py
naga_gwas_rest-0.7.1.dist-info/AUTHORS.rst
naga_gwas_rest-0.7.1.dist-info/LICENSE
naga_gwas_rest-0.7.1.dist-info/METADATA
naga_gwas_rest-0.7.1.dist-info/WHEEL
naga_gwas_rest-0.7.1.dist-info/top_level.txt
naga_gwas_rest-0.7.1.dist-info/RECORD
