Metadata-Version: 2.1
Name: naga-gwas-rest
Version: 0.7.1
Summary: REST service for Network Assisted Genomic Analysis (NAGA)
Home-page: https://github.com/idekerlab/naga-gwas-rest
Author: Chris Churas
Author-email: churas.camera@gmail.com
License: BSD license
Keywords: naga-gwas-rest
Platform: UNKNOWN
Classifier: Development Status :: 2 - Pre-Alpha
Classifier: Intended Audience :: Developers
Classifier: License :: OSI Approved :: BSD License
Classifier: Natural Language :: English
Classifier: Programming Language :: Python :: 3
Classifier: Programming Language :: Python :: 3.4
Classifier: Programming Language :: Python :: 3.5
Classifier: Programming Language :: Python :: 3.6
Classifier: Programming Language :: Python :: 3.7
Requires-Dist: argparse
Requires-Dist: networkx (==1.11)
Requires-Dist: ndex2 (==3.0.0a1)
Requires-Dist: naga-gwas (==0.4.1)
Requires-Dist: numpy
Requires-Dist: flask
Requires-Dist: flask-restplus
Requires-Dist: python-daemon
